leancloud_better_storage/__init__.py
leancloud_better_storage/storage/__init__.py
leancloud_better_storage/storage/err.py
leancloud_better_storage/storage/fields.py
leancloud_better_storage/storage/models.py
leancloud_better_storage/storage/order.py
leancloud_better_storage/storage/pages.py
leancloud_better_storage/storage/query.py
leancloud_better_storage-0.1.7.dist-info/LICENSE
leancloud_better_storage-0.1.7.dist-info/METADATA
leancloud_better_storage-0.1.7.dist-info/WHEEL
leancloud_better_storage-0.1.7.dist-info/top_level.txt
leancloud_better_storage-0.1.7.dist-info/RECORD
