Metadata-Version: 2.1
Name: leancloud-better-storage
Version: 0.1.7
Summary: Better ORM wrapper of leancloud storage python sdk.
Home-page: https://github.com/nnnewb/leancloud-better-storage-python
Author: weak_ptr
Author-email: weak_ptr@outlook.com
License: LGPL
Platform: UNKNOWN
Classifier: Development Status :: 3 - Alpha
Classifier: License :: OSI Approved :: GNU Lesser General Public License v3 (LGPLv3)
Classifier: Programming Language :: Python :: 3.5
Classifier: Programming Language :: Python :: 3.6
Classifier: Operating System :: OS Independent
